picast/__init__.py
picast/__main__.py
picast/dhcpd.py
picast/discovery.py
picast/exceptions.py
picast/logging.ini
picast/player.py
picast/resolutions.json
picast/rtspsink.py
picast/settings.ini
picast/settings.py
picast/video.py
picast/wifip2p.py
picast/wpacli.py
picast-0.4.0.dist-info/LICENSE
picast-0.4.0.dist-info/METADATA
picast-0.4.0.dist-info/WHEEL
picast-0.4.0.dist-info/entry_points.txt
picast-0.4.0.dist-info/top_level.txt
picast-0.4.0.dist-info/RECORD
