Metadata-Version: 2.1
Name: picast
Version: 0.4.0
Summary: A simple wireless display receiver/sink for Raspberry Pi
Home-page: https://github.com/miurahr/picast
Author: Hiroshi Miura
Author-email: miurahr@linux.com
License: GPL3
Platform: UNKNOWN
Classifier: Development Status :: 3 - Alpha
Classifier: Environment :: X11 Applications
Classifier: License :: OSI Approved :: GNU General Public License v3 or later (GPLv3+)
Classifier: Operating System :: POSIX :: Linux
Classifier: Programming Language :: Python
Classifier: Topic :: Utilities
Requires-Dist: zeroconf
Requires-Dist: ifaddr
Provides-Extra: check
Requires-Dist: mypy (>=0.812) ; extra == 'check'
Requires-Dist: mypy-extensions (>=0.4.1) ; extra == 'check'
Requires-Dist: flake8 ; extra == 'check'
Requires-Dist: flake8-black ; extra == 'check'
Requires-Dist: isort (>=5.0.3) ; extra == 'check'
Requires-Dist: pygments ; extra == 'check'
Requires-Dist: readme-renderer ; extra == 'check'
Requires-Dist: docutils ; extra == 'check'
Requires-Dist: check-manifest ; extra == 'check'
Provides-Extra: dev
Requires-Dist: coverage ; extra == 'dev'
Requires-Dist: pyannotate ; extra == 'dev'
Requires-Dist: pytest ; extra == 'dev'
Requires-Dist: pytest-asyncio ; extra == 'dev'
Requires-Dist: pytest-cov ; extra == 'dev'
Provides-Extra: docs
Requires-Dist: sphinx ; extra == 'docs'
Requires-Dist: sphinx-intl ; extra == 'docs'
Requires-Dist: sphinx-py3doc-enhanced-theme ; extra == 'docs'
Requires-Dist: sphinx-rtd-theme ; extra == 'docs'
